{"Caption":"Figure 8: Notation in the Proof of Proposition 1.","ImageText":[{"Text":"Values","TextBB":[260.614,114.634,296.9,126.394],"Rotation":0},{"Text":"A","TextBB":[268.026,143.571,277.935,156.113],"Rotation":0},{"Text":"i","TextBB":[277.935,148.54,281.065,157.248],"Rotation":0},{"Text":"U","TextBB":[438.421,195.428,447.398,207.97],"Rotation":0},{"Text":"i","TextBB":[447.4,200.397,450.53,209.105],"Rotation":0},{"Text":"a","TextBB":[273.577,200.985,280.516,213.526],"Rotation":0},{"Text":"Z","TextBB":[445.83,226.916,454.875,239.457],"Rotation":0},{"Text":"j","TextBB":[454.879,231.886,458.675,240.593],"Rotation":0},{"Text":"a","TextBB":[290.247,232.473,297.186,245.014],"Rotation":0},{"Text":"\u2032","TextBB":[297.186,230.184,299.763,246.212],"Rotation":0},{"Text":"Indices","TextBB":[551.369,244.27,589.105,256.03],"Rotation":0},{"Text":"Y","TextBB":[342.11,273.216,349.778,285.758],"Rotation":0},{"Text":"i","TextBB":[349.778,278.192,352.908,286.899],"Rotation":0},{"Text":"b","TextBB":[532.879,276.921,538.495,289.462],"Rotation":0},{"Text":"B","TextBB":[379.149,288.035,389.192,300.576],"Rotation":0},{"Text":"j","TextBB":[389.192,293.01,392.988,301.717],"Rotation":0},{"Text":"b","TextBB":[568.066,308.409,573.682,320.95],"Rotation":0},{"Text":"\u2032","TextBB":[573.687,306.12,576.265,322.147],"Rotation":0},{"Text":"V","TextBB":[414.341,363.971,422.05,376.512],"Rotation":0},{"Text":"j","TextBB":[422.05,368.946,425.846,377.653],"Rotation":0}],"Mention":["ditional notation in Fig. 8. Recall that a and b denote the sets of elements in v\n","Without loss of generality we consider the case described in Fig. 8 with a, a\u2032 > 0, b, b\u2032 ≤ 0, and\n(a\u2032 − b)2 < (a − b\u2032)2. Due to symmetry, the same argument follows when we consider the other\n"],"Page":10,"Number":8,"Type":"Figure","CaptionBB":[300,399,549,413],"Height":1100,"Width":850,"DPI":100,"ImageBB":[258,112,591,384]}