{"Caption":"   Figure 7. Comparison of adaptation of data bubbles to insertions and deletions when using the fraction of points vs                the extent as quality measures. ","ImageText":[{"Text":"after","TextBB":[296.722,498.572,313.517,506.28],"Rotation":0},{"Text":"insertions","TextBB":[315.88,498.572,352.052,506.28],"Rotation":0},{"Text":"and","TextBB":[354.415,498.572,368.375,506.28],"Rotation":0},{"Text":"deletions","TextBB":[296.722,508.405,330.512,516.113],"Rotation":0},{"Text":"of","TextBB":[332.868,508.405,339.842,516.113],"Rotation":0},{"Text":"points","TextBB":[342.198,508.405,364.675,516.113],"Rotation":0},{"Text":"before","TextBB":[144.555,499.072,168.33,506.78],"Rotation":0},{"Text":"insertions","TextBB":[170.693,499.072,206.865,506.78],"Rotation":0},{"Text":"and","TextBB":[209.228,499.072,223.188,506.78],"Rotation":0},{"Text":"deletions","TextBB":[144.555,508.905,178.345,516.613],"Rotation":0},{"Text":"of","TextBB":[180.702,508.905,187.675,516.613],"Rotation":0},{"Text":"points","TextBB":[190.032,508.905,212.508,516.613],"Rotation":0},{"Text":"a","TextBB":[233.555,530.572,238.188,538.28],"Rotation":0},{"Text":"b","TextBB":[384.722,529.572,389.813,537.28],"Rotation":0},{"Text":"2D","TextBB":[90.2218,560.572,100.905,568.28],"Rotation":0},{"Text":"database","TextBB":[90.2218,570.405,124.698,578.113],"Rotation":0},{"Text":"stationary","TextBB":[144.555,636.572,181.01,644.28],"Rotation":0},{"Text":"cluster","TextBB":[144.555,646.405,169.318,654.113],"Rotation":0},{"Text":"cluster","TextBB":[204.222,636.572,229.042,644.28],"Rotation":0},{"Text":"to","TextBB":[231.402,636.572,238.377,644.28],"Rotation":0},{"Text":"be","TextBB":[240.737,636.572,250.029,644.28],"Rotation":0},{"Text":"deleted","TextBB":[204.222,646.405,231.859,654.113],"Rotation":0},{"Text":"c","TextBB":[233.388,674.072,238.022,681.78],"Rotation":0},{"Text":"newly","TextBB":[335.222,636.572,356.547,644.28],"Rotation":0},{"Text":"inserted","TextBB":[358.88,636.572,388.851,644.28],"Rotation":0},{"Text":"clusters","TextBB":[335.222,646.405,364.209,654.113],"Rotation":0},{"Text":"d","TextBB":[383.055,674.072,388.147,681.78],"Rotation":0},{"Text":"centers","TextBB":[89.7218,692.238,117.182,699.947],"Rotation":0},{"Text":"of","TextBB":[119.538,692.238,126.51,699.947],"Rotation":0},{"Text":"data","TextBB":[89.7218,702.072,106.026,709.78],"Rotation":0},{"Text":"bubbles","TextBB":[108.388,702.072,137.868,709.78],"Rotation":0},{"Text":"using","TextBB":[89.7218,711.905,109.871,719.613],"Rotation":0},{"Text":"extent","TextBB":[112.232,711.905,134.875,719.613],"Rotation":0},{"Text":"as","TextBB":[89.7218,721.738,98.541,729.447],"Rotation":0},{"Text":"quality","TextBB":[100.893,721.738,125.351,729.447],"Rotation":0},{"Text":"measure","TextBB":[89.7218,731.572,122.026,739.28],"Rotation":0},{"Text":"e","TextBB":[236.722,804.03,240.422,811.53],"Rotation":0},{"Text":"f","TextBB":[386.722,804.697,389.497,812.197],"Rotation":0},{"Text":"centers","TextBB":[87.7218,820.738,115.182,828.447],"Rotation":0},{"Text":"of","TextBB":[117.538,820.738,124.51,828.447],"Rotation":0},{"Text":"data","TextBB":[87.7218,830.572,104.026,838.28],"Rotation":0},{"Text":"bubbles","TextBB":[106.388,830.572,135.868,838.28],"Rotation":0},{"Text":"using","TextBB":[87.7218,840.405,107.868,848.113],"Rotation":0},{"Text":"fraction","TextBB":[110.228,840.405,137.863,848.113],"Rotation":0},{"Text":"of","TextBB":[87.7218,850.238,94.6926,857.947],"Rotation":0},{"Text":"points","TextBB":[97.0468,850.238,119.513,857.947],"Rotation":0},{"Text":"as","TextBB":[121.868,850.238,130.688,857.947],"Rotation":0},{"Text":"quality","TextBB":[87.7218,860.072,112.187,867.78],"Rotation":0},{"Text":"measure","TextBB":[87.7218,869.905,120.022,877.613],"Rotation":0}],"Mention":["We first compare the adaptation of the data bubbles to insertions \nand deletions of points when using the fraction of points versus \nthe extent as the measure of the compression quality. We perform \na simple experiment where we demonstrate that if we use the \nextent of a data bubble as the quality measure instead of its \nrelative number of points, the extent quality measure fails to \nproduce a high quality of compression while our quality measure \ndoes not. As Figure 7 shows, we use a simple database that \nconsists of two clusters before any insertions and deletions of \npoints. During the insertions and deletions of points, the cluster in \nthe middle disappears while two new clusters appear in the far \nright.  \n"],"Page":9,"Number":7,"Type":"Figure","CaptionBB":[82,947,400,990],"Height":1100,"Width":850,"DPI":100,"ImageBB":[85,495,400,907]}