{"Caption":"Figure 6: Arity three gates for nonzero even components.","ImageText":[{"Text":"3","TextBB":[286.002,672.315,293.127,681.648],"Rotation":0},{"Text":"3","TextBB":[600.39,681.702,607.515,691.035],"Rotation":0},{"Text":"t","TextBB":[605.759,718.106,610.356,731.037],"Rotation":0},{"Text":"x","TextBB":[282.044,718.844,288.475,731.775],"Rotation":0},{"Text":"c","TextBB":[239.213,733.412,245.436,746.342],"Rotation":0},{"Text":"b","TextBB":[319.945,733.603,327.848,746.533],"Rotation":0},{"Text":"y","TextBB":[253.583,772.009,260.125,784.939],"Rotation":0},{"Text":"2","TextBB":[182.667,807.508,189.792,816.841],"Rotation":0},{"Text":"z","TextBB":[321.684,772.009,327.629,784.939],"Rotation":0},{"Text":"a","TextBB":[287.5,805.273,294.195,818.204],"Rotation":0},{"Text":"1","TextBB":[558.733,782.778,565.858,792.112],"Rotation":0},{"Text":"1","TextBB":[398.487,811.82,405.612,821.154],"Rotation":0},{"Text":"2","TextBB":[538.168,812.623,545.293,821.957],"Rotation":0},{"Text":"1","TextBB":[641.854,782.787,648.979,792.121],"Rotation":0},{"Text":"1","TextBB":[659.367,816.513,666.492,825.847],"Rotation":0}],"Mention":["Proof. For the odd case (0; x; y; 0; z; 0; 0; t) consider Figure 5. Clearly if t 6= 0 the left-hand \fgure\nhas standard signature (0; x; y; 0; z; 0; 0; t) and solves the problem. If t = 0 we use the right-hand\ndiagram.\nFor the even case (t; 0; 0; z; 0; y; x; 0) the signature of the left part of Figure 6 is (ax + by +\ncz; 0; 0; z; 0; y; x; 0) and therefore solves the problem for all values of x; y; z; t by appropriate choice\nof a; b; c, unless x = y = z = 0 and t 6= 0. In that exceptional case we use the right-hand diagram.\n"],"Page":16,"Number":6,"Type":"Figure","CaptionBB":[233,848,615,865],"Height":1100,"Width":850,"DPI":100,"ImageBB":[181,669,666,827]}